{
    "key": "group_6008918a11771",
    "title": "Additional Resources",
    "fields": [
        {
            "key": "field_60008286bed29",
            "label": "Additional Resources Post Object",
            "name": "additional_resources_post_object",
            "type": "post_object",
            "instructions": "Filtered by Resources custom post type",
            "required": 0,
            "conditional_logic": 0,
            "wrapper": {
                "width": "",
                "class": "",
                "id": ""
            },
            "post_type": "",
            "taxonomy": "",
            "allow_null": 0,
            "multiple": 1,
            "return_format": "object",
            "ui": 1
        }
    ],
    "location": [
        [
            {
                "param": "post_type",
                "operator": "==",
                "value": "synack-lp"
            }
        ]
    ],
    "menu_order": 0,
    "position": "normal",
    "style": "default",
    "label_placement": "top",
    "instruction_placement": "label",
    "hide_on_screen": "",
    "active": true,
    "description": "",
    "modified": 1619031538
}